acturate/__init__.py
acturate/rating_engine/__init__.py
acturate/rating_engine/model.py
acturate/rating_engine/nodes.py
acturate/rating_engine/operators.py
acturate/rating_engine/utils.py
acturate-0.1.0.dist-info/licenses/LICENSE
acturate-0.1.0.dist-info/METADATA
acturate-0.1.0.dist-info/WHEEL
acturate-0.1.0.dist-info/top_level.txt
acturate-0.1.0.dist-info/RECORD
