Metadata-Version: 2.4
Name: acturate
Version: 0.1.0
Summary: Tools for pricing actuaries
Author: Ignasi Mañé Bosch
Project-URL: Homepage, https://github.com/imanebosch/acturate
Project-URL: Repository, https://github.com/imanebosch/acturate
Classifier: Programming Language :: Python :: 3.8
Classifier: License :: OSI Approved :: MIT License
Classifier: Operating System :: OS Independent
Requires-Python: >=3.8
License-File: LICENSE
Provides-Extra: dev
Requires-Dist: pytest==8.4.1; extra == "dev"
Requires-Dist: pytest-cov==6.2.1; extra == "dev"
Requires-Dist: pytest-mock==3.14.1; extra == "dev"
Requires-Dist: ruff==0.12.3; extra == "dev"
Requires-Dist: ipython; extra == "dev"
Dynamic: license-file
